README.rst
setup.py
src/CncLibrary/__init__.py
src/CncLibrary/version.py
src/CncLibrary.egg-info/PKG-INFO
src/CncLibrary.egg-info/SOURCES.txt
src/CncLibrary.egg-info/dependency_links.txt
src/CncLibrary.egg-info/requires.txt
src/CncLibrary.egg-info/top_level.txt