Metadata-Version: 1.1
Name: CncLibrary
Version: 0.1-dev
Summary: Robot Framework library for driving CNC mill 
Home-page: https://github.com/Eficode/robotframework-cnclibrary
Author: Eficode Oy
Author-email: info@eficode.com
License: MIT
Keywords: cnc robotframework testing testautomation acceptancetesting atdd bdd
Platform: UNKNOWN
Classifier: Development Status :: 5 - Production/Stable
Classifier: Programming Language :: Python :: 2 :: Only
Classifier: Operating System :: OS Independent
Classifier: Topic :: Software Development :: Testing
Classifier: License :: OSI Approved :: MIT License
